memory.sv

module memory(clk, reset, wr, rd, addr, wdata, rdata, response);

parameter reg [15:0] ADDR_WIDTH=8;
  parameter reg [15:0] DATA_WIDTH=16;
parameter reg [15:0] MEM_SIZE=16;

input clk, reset;
input wr, rd;
input [ADDR_WIDTH-1:0] addr;
input [DATA_WIDTH-1:0] wdata;
output [DATA_WIDTH-1:0] rdata;
output reg response;

  wire [DATA_WIDTH-1:0] rdata;
  reg  [DATA_WIDTH-1:0] mem [MEM_SIZE];
  reg  [DATA_WIDTH-1:0] data_out;
// reg response

reg out_enable;

assign rdata=out_enable? data_out : 'bZ;

// async reset & sync write.

always@(posedge clk or posedge reset) begin
	if(reset) begin
		for(int i=0; i<MEM_SIZE ; i++)
          mem[i]<= 'b0;
	end
    else if(wr) begin
      mem[addr]<=wdata;
		response<=1'b1;
	end
	else response<=1'b0;
end

// sync read.

always @(posedge clk) begin
	if(reset) begin
		data_out<='b0;
		out_enable<=1'b0;
	end
	else if (rd) begin
		data_out<=mem[addr];
		out_enable<=1'b1;
    end  
    else 
		out_enable<=1'b0;
end

endmodule

test.sv
module test; //Automated self test
  
parameter reg [15:0] ADDR_WIDTH=8;
parameter reg [15:0] DATA_WIDTH=16;
parameter reg [15:0] MEM_SIZE=16;
  
reg clk, reset;
reg wr, rd;
reg [ADDR_WIDTH-1:0] addr;
reg [DATA_WIDTH-1:0] wdata;
wire [DATA_WIDTH-1:0] rdata;
wire response;
  
  reg [DATA_WIDTH-1:0] w_d[$], r_d[$]; 
  
  memory DUT(clk, reset, wr, rd, addr, wdata, rdata, response);
  
always #5 clk=~clk;

initial begin
  //$dumpfile("tb.vcd"); $dumpvars(0,test.DUT);
  clk=0;
  reset=0;
  wr=0; rd=0;
  addr=0;
  wdata=0;
  #1 reset=1;
  #1 reset=0;
end
  
initial begin
  repeat(2) @(posedge clk); //wait
  
  wr<=1; //write gen
  for(int i=0;i<MEM_SIZE;i++) begin
  	addr<=i;
  	wdata<=$random;
    @(posedge clk);
    w_d.push_back(wdata);
    @(negedge clk);
  end  
  	wr<=0;
  
  repeat(2) @(posedge clk); //wait
  
  rd<=1; //read gen
  for(int i=0;i<MEM_SIZE;i++) begin
 	 addr<=i;
 	 @(posedge clk);
     @(negedge clk);
     r_d.push_back(rdata);
  end  
  rd<=0;
  
  @(posedge clk);
  $finish;
end

final begin
  $display("\n\t",w_d,"\n\t",r_d); 
  
  if(w_d==r_d) $display("\n-----Success-----\n");
  else $display("\n-----Failure-----\n");
end
 
  
endmodule

tb.vcd
$date
	Sun Jun 18 05:41:33 2023
$end
$version
	ModelSim Version 10.5b
$end
$timescale
	1ps
$end

$scope module test $end

$scope module DUT $end
$var parameter 16 ! ADDR_WIDTH $end
$var parameter 16 " DATA_WIDTH $end
$var parameter 16 # MEM_SIZE $end
$var wire 1 $ clk $end
$var wire 1 % reset $end
$var wire 1 & wr $end
$var wire 1 ' rd $end
$var wire 1 ( addr [7] $end
$var wire 1 ) addr [6] $end
$var wire 1 * addr [5] $end
$var wire 1 + addr [4] $end
$var wire 1 , addr [3] $end
$var wire 1 - addr [2] $end
$var wire 1 . addr [1] $end
$var wire 1 / addr [0] $end
$var wire 1 0 wdata [15] $end
$var wire 1 1 wdata [14] $end
$var wire 1 2 wdata [13] $end
$var wire 1 3 wdata [12] $end
$var wire 1 4 wdata [11] $end
$var wire 1 5 wdata [10] $end
$var wire 1 6 wdata [9] $end
$var wire 1 7 wdata [8] $end
$var wire 1 8 wdata [7] $end
$var wire 1 9 wdata [6] $end
$var wire 1 : wdata [5] $end
$var wire 1 ; wdata [4] $end
$var wire 1 < wdata [3] $end
$var wire 1 = wdata [2] $end
$var wire 1 > wdata [1] $end
$var wire 1 ? wdata [0] $end
$var wire 1 @ rdata [15] $end
$var wire 1 A rdata [14] $end
$var wire 1 B rdata [13] $end
$var wire 1 C rdata [12] $end
$var wire 1 D rdata [11] $end
$var wire 1 E rdata [10] $end
$var wire 1 F rdata [9] $end
$var wire 1 G rdata [8] $end
$var wire 1 H rdata [7] $end
$var wire 1 I rdata [6] $end
$var wire 1 J rdata [5] $end
$var wire 1 K rdata [4] $end
$var wire 1 L rdata [3] $end
$var wire 1 M rdata [2] $end
$var wire 1 N rdata [1] $end
$var wire 1 O rdata [0] $end
$var reg 1 P response $end
$var reg 16 Q data_out [15:0] $end
$var reg 1 R out_enable $end
$upscope $end
$upscope $end
$enddefinitions $end
#0
$dumpvars
xP
bx Q
xR
b1000 !
b10000 "
b10000 #
xO
xN
xM
xL
xK
xJ
xI
xH
xG
xF
xE
xD
xC
xB
xA
x@
0$
0%
0&
0'
0/
0.
0-
0,
0+
0*
0)
0(
0?
0>
0=
0<
0;
0:
09
08
07
06
05
04
03
02
01
00
$end
#1
1%
#2
0%
#5
1$
0P
0R
zO
zN
zM
zL
zK
zJ
zI
zH
zG
zF
zE
zD
zC
zB
zA
z@
#10
0$
#15
1$
1&
1=
1:
17
15
13
12
#20
0$
#25
1$
1P
#30
0$
1?
0=
0:
18
07
16
14
02
11
1/
#35
1$
#40
0$
1<
08
04
10
0/
1.
#45
1$
#50
0$
1>
0<
1:
19
00
1/
#55
1$
#60
0$
0>
1=
1<
0:
09
17
05
14
12
0/
0.
1-
#65
1$
#70
0$
18
06
02
01
10
1/
#75
1$
#80
0$
0<
1:
19
08
07
15
04
03
0/
1.
#85
1$
#90
0$
0?
1>
0=
1;
0:
09
16
05
13
11
00
1/
#95
1$
#100
0$
1?
0>
0;
17
03
12
10
0/
0.
0-
1,
#105
1$
#110
0$
1=
1<
06
15
14
02
1/
#115
1$
#120
0$
0?
1>
0<
1;
1:
19
05
04
13
12
0/
1.
#125
1$
#130
0$
1?
0>
1<
09
15
14
03
02
1/
#135
1$
#140
0$
0;
19
18
16
04
13
00
0/
0.
1-
#145
1$
#150
0$
0?
0:
09
12
10
1/
#155
1$
#160
0$
1?
0=
1;
1:
19
06
05
14
03
0/
1.
#165
1$
#170
0$
0?
1>
1=
0<
0;
0:
07
15
04
01
00
1/
#175
1$
#180
0$
0&
#185
1$
0P
#190
0$
#195
1$
1'
0/
0.
0-
0,
#200
0$
#205
1$
b11010100100100 Q
1R
0O
0N
1M
0L
0K
1J
0I
0H
1G
0F
1E
0D
1C
1B
0A
0@
#210
0$
1/
#215
1$
b101111010000001 Q
1O
0M
0J
1H
0G
1F
1D
0B
1A
#220
0$
0/
1.
#225
1$
b1101011000001001 Q
1L
0H
0D
1@
#230
0$
1/
#235
1$
b101011001100011 Q
1N
0L
1J
1I
0@
#240
0$
0/
0.
1-
#245
1$
b111101100001101 Q
0N
1M
1L
0J
0I
1G
0E
1D
1B
#250
0$
1/
#255
1$
b1001100110001101 Q
1H
0F
0B
0A
1@
#260
0$
0/
1.
#265
1$
b1000010001100101 Q
0L
1J
1I
0H
0G
1E
0D
0C
#270
0$
1/
#275
1$
b101001000010010 Q
0O
1N
0M
1K
0J
0I
1F
0E
1C
1A
0@
#280
0$
0/
0.
0-
1,
#285
1$
b1110001100000001 Q
1O
0N
0K
1G
0C
1B
1@
#290
0$
1/
#295
1$
b1100110100001101 Q
1M
1L
0F
1E
1D
0B
#300
0$
0/
1.
#305
1$
b1111000101110110 Q
0O
1N
0L
1K
1J
1I
0E
0D
1C
1B
#310
0$
1/
#315
1$
b1100110100111101 Q
1O
0N
1L
0I
1E
1D
0C
0B
#320
0$
0/
0.
1-
#325
1$
b101011111101101 Q
0K
1I
1H
1F
0D
1C
0@
#330
0$
1/
#335
1$
b1111011110001100 Q
0O
0J
0I
1B
1@
#340
0$
0/
1.
#345
1$
b1110100111111001 Q
1O
0M
1K
1J
1I
0F
0E
1D
0C
#350
0$
1/
#355
1$
b10010011000110 Q
0O
1N
1M
0L
0K
0J
0G
1E
0D
0A
0@
#360
0$
0'
